solcore-5.10.1.dist-info/WHEEL
solcore-5.10.1.dist-info/GNU-LGPL.txt
solcore-5.10.1.dist-info/RECORD
solcore-5.10.1.dist-info/METADATA
solcore/crystals.py
solcore/config_tools.py
solcore/state.py
solcore/structure.py
solcore/source_managed_class.py
solcore/solar_cell_solver.py
solcore/interpolate.py
solcore/smooth.py
solcore/singleton.py
solcore/registries.py
solcore/__init__.py
solcore/science_tracker.py
solcore/solar_cell.py
solcore/solcore_config.txt
solcore/strain_balancing.py
solcore/constants.py
solcore/quantum_mechanics/strain.py
solcore/quantum_mechanics/graphics.py
solcore/quantum_mechanics/kp_bulk.py
solcore/quantum_mechanics/high_level_kp_QW.py
solcore/quantum_mechanics/__init__.py
solcore/quantum_mechanics/structure_utilities.py
solcore/quantum_mechanics/kp_QW.py
solcore/quantum_mechanics/heterostructure_alignment.py
solcore/quantum_mechanics/potential_utilities.py
solcore/parameter_system/calculable_parameters.txt
solcore/parameter_system/__init__.py
solcore/parameter_system/parameter_system.py
solcore/graphing/graph_support.py
solcore/graphing/Custom_Colours.py
solcore/graphing/graph_lines.py
solcore/graphing/__init__.py
solcore/graphing/Colours.txt
solcore/graphing/graph.py
solcore/analytic_solar_cells/IV.py
solcore/analytic_solar_cells/diode_equation.py
solcore/analytic_solar_cells/detailed_balance.py
solcore/analytic_solar_cells/__init__.py
solcore/analytic_solar_cells/tunnel_junctions.py
solcore/analytic_solar_cells/QE.py
solcore/analytic_solar_cells/depletion_approximation.py
solcore/optimization/__init__.py
solcore/optimization/differential_evolution.py
solcore/sesame_drift_diffusion/solve_pdd.py
solcore/sesame_drift_diffusion/process_structure.py
solcore/sesame_drift_diffusion/__init__.py
solcore/light_source/SPCTRAL_si_units.txt
solcore/light_source/spectral2.py
solcore/light_source/__init__.py
solcore/light_source/astmg173.csv
solcore/light_source/smarts.py
solcore/light_source/light_source.py
solcore/data_analysis_tools/__init__.py
solcore/data_analysis_tools/ellipsometry_analysis.py
