Metadata-Version: 2.1
Name: solcore
Version: 5.10.1
Summary: Python-based solar cell simulator
Keywords: photovoltaics,modelling,physics
Author-Email: The Quantum Photovoltaics Group <nekins@unsw.edu.au>
License:                    GNU LESSER GENERAL PUBLIC LICENSE
Classifier: Development Status :: 5 - Production/Stable
Classifier: Intended Audience :: Science/Research
Classifier: License :: OSI Approved
Classifier: License :: OSI Approved :: GNU Lesser General Public License v3 or later (LGPLv3+)
Classifier: Natural Language :: English
Classifier: Operating System :: OS Independent
Classifier: Programming Language :: Python
Classifier: Programming Language :: Python :: 3
Classifier: Topic :: Scientific/Engineering
Classifier: Topic :: Scientific/Engineering :: Physics
Project-URL: homepage, https://www.solcore.solar/
Project-URL: documentation, http://solcore5.readthedocs.io
Project-URL: repository, https://github.com/qpv-research-group/solcore5
Project-URL: changelog, https://github.com/me/spam/blob/master/CHANGELOG.md
Requires-Python: >=3.9
Requires-Dist: numpy>=2.0.0
Requires-Dist: matplotlib
Requires-Dist: scipy
Requires-Dist: tmm
Requires-Dist: natsort
Requires-Dist: regex
Requires-Dist: cycler
Requires-Dist: pyyaml
Requires-Dist: yabox
Requires-Dist: joblib
Requires-Dist: solsesame==2.1a1
Provides-Extra: test
Requires-Dist: pytest; extra == "test"
Requires-Dist: pytest-cov; extra == "test"
Requires-Dist: pytest-mock; extra == "test"
Requires-Dist: nbconvert; extra == "test"
Requires-Dist: nbformat; extra == "test"
Requires-Dist: pytest-rerunfailures; extra == "test"
Requires-Dist: pytest-xdist; extra == "test"
Provides-Extra: doc
Requires-Dist: Sphinx; extra == "doc"
Requires-Dist: recommonmark; extra == "doc"
Provides-Extra: dev
Requires-Dist: pre-commit; extra == "dev"
